mwt_games_manager/__init__.py
mwt_games_manager/controller.py
mwt_games_manager/managers.py
mwt_games_manager/product_manager.py
mwt_games_manager/utils.py
mwt_games_manager/models/__init__.py
mwt_games_manager/models/feature.py
mwt_games_manager/models/game_history.py
mwt_games_manager/models/general_game_data.py
mwt_games_manager/models/product.py
mwt_games_manager/models/public_game_user.py
mwt_games_manager/models/user.py
mwt_games_manager-1.0.17.dist-info/WHEEL
mwt_games_manager-1.0.17.dist-info/METADATA
mwt_games_manager-1.0.17.dist-info/RECORD
