Metadata-Version: 2.4
Name: mwt_games_manager
Version: 1.0.17
Summary: Manages users game data in MWT games
Author-email: Mani Fatemi <mani@milkywaytrail.ca>
Requires-Python: >=3.8
Classifier: Programming Language :: Python :: 3
Classifier: License :: OSI Approved :: MIT License
Classifier: Operating System :: OS Independent
Requires-Dist: firebase-admin
Requires-Dist: flask-bcrypt
